pyllot/__about__.py
pyllot/__init__.py
pyllot/_stack.py
pyllot/direction.py
pyllot/py.typed
pyllot/router.py
pyllot/transition.py
pyllot/abc/__init__.py
pyllot/abc/factory.py
pyllot/abc/presenter.py
pyllot/abc/screen.py
pyllot-0.1.0.dist-info/METADATA
pyllot-0.1.0.dist-info/WHEEL
pyllot-0.1.0.dist-info/licenses/LICENSE
pyllot-0.1.0.dist-info/RECORD
