Metadata-Version: 2.1
Name: pyllot
Version: 0.1.0
Summary: Application routing with event-driven finite-state machine.
Project-URL: Documentation, https://pyllot.tombartk.com
Project-URL: Issues, https://github.com/tom-bartk/pyllot/issues
Project-URL: Source, https://github.com/tom-bartk/pyllot
Author-email: tombartk <tom.bartk@proton.me>
License-Expression: AGPL-3.0-or-later
License-File: LICENSE
Classifier: Development Status :: 4 - Beta
Classifier: Intended Audience :: Developers
Classifier: License :: OSI Approved :: GNU Affero General Public License v3 or later (AGPLv3+)
Classifier: Programming Language :: Python
Classifier: Programming Language :: Python :: 3.10
Classifier: Programming Language :: Python :: 3.11
Classifier: Programming Language :: Python :: 3.12
Classifier: Topic :: Software Development
Classifier: Typing :: Typed
Requires-Python: >=3.10
